tickerbar/__init__.py
tickerbar/config.json
tickerbar/quotes.json
tickerbar-0.9.data/scripts/tickerbar
tickerbar-0.9.dist-info/METADATA
tickerbar-0.9.dist-info/RECORD
tickerbar-0.9.dist-info/WHEEL
tickerbar-0.9.dist-info/top_level.txt
