Metadata-Version: 2.1
Name: tickerbar
Version: 0.9
Summary: Stock quotes on the mac touch bar
Home-page: https://github.com/etaba/tickerbar
Author: Eric Taba
Author-email: eptaba@gmail.com
License: UNKNOWN
Download-URL: https://github.com/etaba/tickerbar/tarball/0.1
Keywords: mac,touch bar,stock,stocks,macbook,ticker,quotes
Platform: UNKNOWN
Requires-Dist: pinance
